CHANGELOG.md
ghisa/__init__.py
ghisa/config.py
ghisa/console/__init__.py
ghisa/console/application.py
ghisa/console/gui.py
ghisa/console/profile.py
ghisa/console/repo.py
ghisa/core/__init__.py
ghisa/core/defaults.py
ghisa/core/gh/__init__.py
ghisa/core/gh/extract.py
ghisa/core/gh/gh.py
ghisa/core/gh/load.py
ghisa/core/gh/urls.py
ghisa/core/ghisa.py
ghisa/core/helpers.py
ghisa/core/local/__init__.py
ghisa/core/local/builtins_modules.py
ghisa/core/local/extract.py
ghisa/core/local/helpers.py
ghisa/core/local/load.py
ghisa/core/local/local.py
ghisa/core/local/pypi_list.py
ghisa/core/local/transform.py
ghisa/core/profile.py
ghisa/core/repo.py
ghisa/core/validators.py
ghisa/gui/__init__.py
ghisa/gui/front.py
ghisa/logger.py
ghisa/sandbox/github.py
ghisa/validators.py
ghisa-0.0.1.dist-info/LICENSE
ghisa-0.0.1.dist-info/METADATA
ghisa-0.0.1.dist-info/WHEEL
ghisa-0.0.1.dist-info/RECORD
