Metadata-Version: 2.1
Name: ghisa
Version: 0.0.1
Summary: ghisa is a GitHub Import Stats Analyzer for pythonistas
Home-page: https://alexandregazagnes.github.io/ghisa/
License: BSD-3-Clause
Keywords: python,git,tool,utils,github,stats,analyzer,import,export,data,analysis
Author: AlexandreGazagnes
Author-email: alex@gazagnes.net
Maintainer: AlexandreGazagnes
Maintainer-email: alex@gazagnes.net
Requires-Python: ==3.10.12
Classifier: Development Status :: 5 - Production/Stable
Classifier: Environment :: Other Environment
Classifier: Intended Audience :: Developers
Classifier: Intended Audience :: Education
Classifier: Intended Audience :: Information Technology
Classifier: License :: OSI Approved :: BSD License
Classifier: Programming Language :: Python
Classifier: Programming Language :: Python :: 3
Classifier: Programming Language :: Python :: 3 :: Only
Classifier: Topic :: Software Development :: Libraries :: Python Modules
Requires-Dist: cleo (>=2.1.0,<3.0.0)
Project-URL: Changelog, https://alexandregazagnes.github.io/ghisa/CHANGELOG/
Project-URL: Documentation, https://alexandregazagnes.github.io/ghisa/
Project-URL: Issues, https://github.com/AlexandreGazagnes/ghisa/issues
Project-URL: Repository, https://github.com/AlexandreGazagnes/ghisa/tree/main
